odoo/addons/account_payment_sale/README.rst
odoo/addons/account_payment_sale/__init__.py
odoo/addons/account_payment_sale/__manifest__.py
odoo/addons/account_payment_sale/i18n/account_payment_sale.pot
odoo/addons/account_payment_sale/i18n/ca.po
odoo/addons/account_payment_sale/i18n/ca_ES.po
odoo/addons/account_payment_sale/i18n/da_DK.po
odoo/addons/account_payment_sale/i18n/de.po
odoo/addons/account_payment_sale/i18n/es.po
odoo/addons/account_payment_sale/i18n/fr.po
odoo/addons/account_payment_sale/i18n/nl.po
odoo/addons/account_payment_sale/i18n/nl_NL.po
odoo/addons/account_payment_sale/i18n/pt_BR.po
odoo/addons/account_payment_sale/i18n/sl.po
odoo/addons/account_payment_sale/i18n/zh_CN.po
odoo/addons/account_payment_sale/models/__init__.py
odoo/addons/account_payment_sale/models/sale_order.py
odoo/addons/account_payment_sale/static/description/icon.png
odoo/addons/account_payment_sale/static/description/index.html
odoo/addons/account_payment_sale/tests/__init__.py
odoo/addons/account_payment_sale/tests/common.py
odoo/addons/account_payment_sale/tests/test_sale_order.py
odoo/addons/account_payment_sale/views/sale_order_view.xml
odoo/addons/account_payment_sale/views/sale_report_templates.xml
odoo/addons/account_payment_sale/wizard/__init__.py
odoo/addons/account_payment_sale/wizard/sale_make_invoice_advance.py
odoo12_addon_account_payment_sale-12.0.1.1.3.dist-info/METADATA
odoo12_addon_account_payment_sale-12.0.1.1.3.dist-info/WHEEL
odoo12_addon_account_payment_sale-12.0.1.1.3.dist-info/top_level.txt
odoo12_addon_account_payment_sale-12.0.1.1.3.dist-info/RECORD
